signal_mcp/__init__.py
signal_mcp/main.py
mseep_signal_mcp-0.1.4.dist-info/METADATA
mseep_signal_mcp-0.1.4.dist-info/WHEEL
mseep_signal_mcp-0.1.4.dist-info/entry_points.txt
mseep_signal_mcp-0.1.4.dist-info/RECORD
